traffic_light_controller.v
module traffic_light_controller(
    input wire clk,
    input wire rst,
    input wire night_mode,
    input wire sensor_NS,
    input wire sensor_EW,
    input wire ped_NS,
    input wire ped_EW,
    output reg [2:0] light_NS,
    output reg [2:0] light_EW,
    output reg ped_signal_NS,
    output reg ped_signal_EW
);

    // State encoding
    parameter G1 = 3'd0, Y1 = 3'd1, R1 = 3'd2,
              G2 = 3'd3, Y2 = 3'd4, R2 = 3'd5,
              BLINK = 3'd6;

    reg [2:0] state, next_state;
    reg [7:0] timer;

    // Timing parameters
    parameter GREEN_TIME = 8'd100;
    parameter YELLOW_TIME = 8'd30;
    parameter RED_TIME = 8'd20;
    parameter BLINK_TIME = 8'd10;

    // Clocked state machine
    always @(posedge clk or posedge rst) begin
        if (rst) begin
            state <= G1;
            timer <= 0;
        end else begin
            if (timer >= (night_mode ? BLINK_TIME :
                         (state == G1 && sensor_NS) || (state == G2 && sensor_EW) ? GREEN_TIME :
                         (state == Y1 || state == Y2) ? YELLOW_TIME : RED_TIME)) begin
                state <= next_state;
                timer <= 0;
            end else begin
                timer <= timer + 1;
            end
        end
    end

    // Combinational logic
    always @(*) begin
        // Defaults
        light_NS = 3'b001; // Red
        light_EW = 3'b001;
        ped_signal_NS = 0;
        ped_signal_EW = 0;
        next_state = state;

        case (state)
            G1: begin
                light_NS = 3'b100; // Green NS
                light_EW = 3'b001; // Red EW
                if (ped_NS) ped_signal_NS = 1;
                next_state = Y1;
            end
            Y1: begin
                light_NS = 3'b010; // Yellow NS
                light_EW = 3'b001;
                next_state = R1;
            end
            R1: begin
                light_NS = 3'b001;
                light_EW = 3'b001;
                next_state = G2;
            end
            G2: begin
                light_NS = 3'b001;
                light_EW = 3'b100; // Green EW
                if (ped_EW) ped_signal_EW = 1;
                next_state = Y2;
            end
            Y2: begin
                light_NS = 3'b001;
                light_EW = 3'b010; // Yellow EW
                next_state = R2;
            end
            R2: begin
                light_NS = 3'b001;
                light_EW = 3'b001;
                next_state = G1;
            end
            BLINK: begin
                light_NS = 3'b010; // Blinking Yellow (simulate by constant)
                light_EW = 3'b010;
                next_state = BLINK;
            end
            default: next_state = G1;
        endcase

        if (night_mode)
            next_state = BLINK;
    end

endmodule

tb_traffic_light.v
`timescale 1ns / 1ps

module tb_traffic_light;

    reg clk, rst;
    reg sensor_NS, sensor_EW;
    reg ped_NS, ped_EW;
    reg night_mode;

    wire [2:0] light_NS, light_EW;
    wire ped_signal_NS, ped_signal_EW;

    traffic_light_controller uut (
        .clk(clk),
        .rst(rst),
        .sensor_NS(sensor_NS),
        .sensor_EW(sensor_EW),
        .ped_NS(ped_NS),
        .ped_EW(ped_EW),
        .night_mode(night_mode),
        .light_NS(light_NS),
        .light_EW(light_EW),
        .ped_signal_NS(ped_signal_NS),
        .ped_signal_EW(ped_signal_EW)
    );

    // Clock generator
    always #5 clk = ~clk;  // 100MHz clock

    initial begin
        $dumpfile("traffic_wave.vcd");
        $dumpvars(0, tb_traffic_light);

        clk = 0; rst = 1;
        sensor_NS = 0; sensor_EW = 0;
        ped_NS = 0; ped_EW = 0;
        night_mode = 0;

        #20 rst = 0;

        // Simulate normal day operation
        #50 sensor_EW = 1;
        #100 sensor_EW = 0;

        #50 ped_NS = 1;
        #100 ped_NS = 0;

        #50 ped_EW = 1;
        #100 ped_EW = 0;

        // Simulate night mode
        #200 night_mode = 1;
        #1000 night_mode = 0;

        #500 $finish;
    end

endmodule

traffic_wave.vcd
$date
	Thu Apr 17 10:53:24 2025
$end
$version
	Icarus Verilog
$end
$timescale
	1ps
$end
$scope module tb_traffic_light $end
$var wire 1 ! ped_signal_NS $end
$var wire 1 " ped_signal_EW $end
$var wire 3 # light_NS [2:0] $end
$var wire 3 $ light_EW [2:0] $end
$var reg 1 % clk $end
$var reg 1 & night_mode $end
$var reg 1 ' ped_EW $end
$var reg 1 ( ped_NS $end
$var reg 1 ) rst $end
$var reg 1 * sensor_EW $end
$var reg 1 + sensor_NS $end
$scope module uut $end
$var wire 1 % clk $end
$var wire 1 & night_mode $end
$var wire 1 ' ped_EW $end
$var wire 1 ( ped_NS $end
$var wire 1 ) rst $end
$var wire 1 * sensor_EW $end
$var wire 1 + sensor_NS $end
$var parameter 3 , BLINK $end
$var parameter 8 - BLINK_TIME $end
$var parameter 3 . G1 $end
$var parameter 3 / G2 $end
$var parameter 8 0 GREEN_TIME $end
$var parameter 3 1 R1 $end
$var parameter 3 2 R2 $end
$var parameter 8 3 RED_TIME $end
$var parameter 3 4 Y1 $end
$var parameter 3 5 Y2 $end
$var parameter 8 6 YELLOW_TIME $end
$var reg 3 7 light_EW [2:0] $end
$var reg 3 8 light_NS [2:0] $end
$var reg 3 9 next_state [2:0] $end
$var reg 1 " ped_signal_EW $end
$var reg 1 ! ped_signal_NS $end
$var reg 3 : state [2:0] $end
$var reg 8 ; timer [7:0] $end
$upscope $end
$upscope $end
$enddefinitions $end
$comment Show the parameter values. $end
$dumpall
b11110 6
b100 5
b1 4
b10100 3
b101 2
b10 1
b1100100 0
b11 /
b0 .
b1010 -
b110 ,
$end
#0
$dumpvars
b0 ;
b0 :
b1 9
b100 8
b1 7
0+
0*
1)
0(
0'
0&
0%
b1 $
b100 #
0"
0!
$end
#5000
1%
#10000
0%
#15000
1%
#20000
0%
0)
#25000
b1 ;
1%
#30000
0%
#35000
b10 ;
1%
#40000
0%
#45000
b11 ;
1%
#50000
0%
#55000
b100 ;
1%
#60000
0%
#65000
b101 ;
1%
#70000
0%
1*
#75000
b110 ;
1%
#80000
0%
#85000
b111 ;
1%
#90000
0%
#95000
b1000 ;
1%
#100000
0%
#105000
b1001 ;
1%
#110000
0%
#115000
b1010 ;
1%
#120000
0%
#125000
b1011 ;
1%
#130000
0%
#135000
b1100 ;
1%
#140000
0%
#145000
b1101 ;
1%
#150000
0%
#155000
b1110 ;
1%
#160000
0%
#165000
b1111 ;
1%
#170000
0%
0*
#175000
b10000 ;
1%
#180000
0%
#185000
b10001 ;
1%
#190000
0%
#195000
b10010 ;
1%
#200000
0%
#205000
b10011 ;
1%
#210000
0%
#215000
b10100 ;
1%
#220000
1!
b1 9
b100 #
b100 8
0%
1(
#225000
b10 9
0!
b10 #
b10 8
b0 ;
b1 :
1%
#230000
0%
#235000
b1 ;
1%
#240000
0%
#245000
b10 ;
1%
#250000
0%
#255000
b11 ;
1%
#260000
0%
#265000
b100 ;
1%
#270000
0%
#275000
b101 ;
1%
#280000
0%
#285000
b110 ;
1%
#290000
0%
#295000
b111 ;
1%
#300000
0%
#305000
b1000 ;
1%
#310000
0%
#315000
b1001 ;
1%
#320000
b10 9
b10 #
b10 8
0%
0(
#325000
b1010 ;
1%
#330000
0%
#335000
b1011 ;
1%
#340000
0%
#345000
b1100 ;
1%
#350000
0%
#355000
b1101 ;
1%
#360000
0%
#365000
b1110 ;
1%
#370000
b10 9
b10 #
b10 8
0%
1'
#375000
b1111 ;
1%
#380000
0%
#385000
b10000 ;
1%
#390000
0%
#395000
b10001 ;
1%
#400000
0%
#405000
b10010 ;
1%
#410000
0%
#415000
b10011 ;
1%
#420000
0%
#425000
b10100 ;
1%
#430000
0%
#435000
b10101 ;
1%
#440000
0%
#445000
b10110 ;
1%
#450000
0%
#455000
b10111 ;
1%
#460000
0%
#465000
b11000 ;
1%
#470000
b10 9
b10 #
b10 8
0%
0'
#475000
b11001 ;
1%
#480000
0%
#485000
b11010 ;
1%
#490000
0%
#495000
b11011 ;
1%
#500000
0%
#505000
b11100 ;
1%
#510000
0%
#515000
b11101 ;
1%
#520000
0%
#525000
b11110 ;
1%
#530000
0%
#535000
b11 9
b1 #
b1 8
b0 ;
b10 :
1%
#540000
0%
#545000
b1 ;
1%
#550000
0%
#555000
b10 ;
1%
#560000
0%
#565000
b11 ;
1%
#570000
0%
#575000
b100 ;
1%
#580000
0%
#585000
b101 ;
1%
#590000
0%
#595000
b110 ;
1%
#600000
0%
#605000
b111 ;
1%
#610000
0%
#615000
b1000 ;
1%
#620000
0%
#625000
b1001 ;
1%
#630000
0%
#635000
b1010 ;
1%
#640000
0%
#645000
b1011 ;
1%
#650000
0%
#655000
b1100 ;
1%
#660000
0%
#665000
b1101 ;
1%
#670000
b110 9
0%
1&
#675000
b10 $
b10 7
b10 #
b10 8
b0 ;
b110 :
1%
#680000
0%
#685000
b1 ;
1%
#690000
0%
#695000
b10 ;
1%
#700000
0%
#705000
b11 ;
1%
#710000
0%
#715000
b100 ;
1%
#720000
0%
#725000
b101 ;
1%
#730000
0%
#735000
b110 ;
1%
#740000
0%
#745000
b111 ;
1%
#750000
0%
#755000
b1000 ;
1%
#760000
0%
#765000
b1001 ;
1%
#770000
0%
#775000
b1010 ;
1%
#780000
0%
#785000
b0 ;
1%
#790000
0%
#795000
b1 ;
1%
#800000
0%
#805000
b10 ;
1%
#810000
0%
#815000
b11 ;
1%
#820000
0%
#825000
b100 ;
1%
#830000
0%
#835000
b101 ;
1%
#840000
0%
#845000
b110 ;
1%
#850000
0%
#855000
b111 ;
1%
#860000
0%
#865000
b1000 ;
1%
#870000
0%
#875000
b1001 ;
1%
#880000
0%
#885000
b1010 ;
1%
#890000
0%
#895000
b0 ;
1%
#900000
0%
#905000
b1 ;
1%
#910000
0%
#915000
b10 ;
1%
#920000
0%
#925000
b11 ;
1%
#930000
0%
#935000
b100 ;
1%
#940000
0%
#945000
b101 ;
1%
#950000
0%
#955000
b110 ;
1%
#960000
0%
#965000
b111 ;
1%
#970000
0%
#975000
b1000 ;
1%
#980000
0%
#985000
b1001 ;
1%
#990000
0%
#995000
b1010 ;
1%
#1000000
0%
#1005000
b0 ;
1%
#1010000
0%
#1015000
b1 ;
1%
#1020000
0%
#1025000
b10 ;
1%
#1030000
0%
#1035000
b11 ;
1%
#1040000
0%
#1045000
b100 ;
1%
#1050000
0%
#1055000
b101 ;
1%
#1060000
0%
#1065000
b110 ;
1%
#1070000
0%
#1075000
b111 ;
1%
#1080000
0%
#1085000
b1000 ;
1%
#1090000
0%
#1095000
b1001 ;
1%
#1100000
0%
#1105000
b1010 ;
1%
#1110000
0%
#1115000
b0 ;
1%
#1120000
0%
#1125000
b1 ;
1%
#1130000
0%
#1135000
b10 ;
1%
#1140000
0%
#1145000
b11 ;
1%
#1150000
0%
#1155000
b100 ;
1%
#1160000
0%
#1165000
b101 ;
1%
#1170000
0%
#1175000
b110 ;
1%
#1180000
0%
#1185000
b111 ;
1%
#1190000
0%
#1195000
b1000 ;
1%
#1200000
0%
#1205000
b1001 ;
1%
#1210000
0%
#1215000
b1010 ;
1%
#1220000
0%
#1225000
b0 ;
1%
#1230000
0%
#1235000
b1 ;
1%
#1240000
0%
#1245000
b10 ;
1%
#1250000
0%
#1255000
b11 ;
1%
#1260000
0%
#1265000
b100 ;
1%
#1270000
0%
#1275000
b101 ;
1%
#1280000
0%
#1285000
b110 ;
1%
#1290000
0%
#1295000
b111 ;
1%
#1300000
0%
#1305000
b1000 ;
1%
#1310000
0%
#1315000
b1001 ;
1%
#1320000
0%
#1325000
b1010 ;
1%
#1330000
0%
#1335000
b0 ;
1%
#1340000
0%
#1345000
b1 ;
1%
#1350000
0%
#1355000
b10 ;
1%
#1360000
0%
#1365000
b11 ;
1%
#1370000
0%
#1375000
b100 ;
1%
#1380000
0%
#1385000
b101 ;
1%
#1390000
0%
#1395000
b110 ;
1%
#1400000
0%
#1405000
b111 ;
1%
#1410000
0%
#1415000
b1000 ;
1%
#1420000
0%
#1425000
b1001 ;
1%
#1430000
0%
#1435000
b1010 ;
1%
#1440000
0%
#1445000
b0 ;
1%
#1450000
0%
#1455000
b1 ;
1%
#1460000
0%
#1465000
b10 ;
1%
#1470000
0%
#1475000
b11 ;
1%
#1480000
0%
#1485000
b100 ;
1%
#1490000
0%
#1495000
b101 ;
1%
#1500000
0%
#1505000
b110 ;
1%
#1510000
0%
#1515000
b111 ;
1%
#1520000
0%
#1525000
b1000 ;
1%
#1530000
0%
#1535000
b1001 ;
1%
#1540000
0%
#1545000
b1010 ;
1%
#1550000
0%
#1555000
b0 ;
1%
#1560000
0%
#1565000
b1 ;
1%
#1570000
0%
#1575000
b10 ;
1%
#1580000
0%
#1585000
b11 ;
1%
#1590000
0%
#1595000
b100 ;
1%
#1600000
0%
#1605000
b101 ;
1%
#1610000
0%
#1615000
b110 ;
1%
#1620000
0%
#1625000
b111 ;
1%
#1630000
0%
#1635000
b1000 ;
1%
#1640000
0%
#1645000
b1001 ;
1%
#1650000
0%
#1655000
b1010 ;
1%
#1660000
0%
#1665000
b0 ;
1%
#1670000
b10 $
b10 7
b10 #
b10 8
0%
0&
#1675000
b1 ;
1%
#1680000
0%
#1685000
b10 ;
1%
#1690000
0%
#1695000
b11 ;
1%
#1700000
0%
#1705000
b100 ;
1%
#1710000
0%
#1715000
b101 ;
1%
#1720000
0%
#1725000
b110 ;
1%
#1730000
0%
#1735000
b111 ;
1%
#1740000
0%
#1745000
b1000 ;
1%
#1750000
0%
#1755000
b1001 ;
1%
#1760000
0%
#1765000
b1010 ;
1%
#1770000
0%
#1775000
b1011 ;
1%
#1780000
0%
#1785000
b1100 ;
1%
#1790000
0%
#1795000
b1101 ;
1%
#1800000
0%
#1805000
b1110 ;
1%
#1810000
0%
#1815000
b1111 ;
1%
#1820000
0%
#1825000
b10000 ;
1%
#1830000
0%
#1835000
b10001 ;
1%
#1840000
0%
#1845000
b10010 ;
1%
#1850000
0%
#1855000
b10011 ;
1%
#1860000
0%
#1865000
b10100 ;
1%
#1870000
0%
#1875000
b0 ;
1%
#1880000
0%
#1885000
b1 ;
1%
#1890000
0%
#1895000
b10 ;
1%
#1900000
0%
#1905000
b11 ;
1%
#1910000
0%
#1915000
b100 ;
1%
#1920000
0%
#1925000
b101 ;
1%
#1930000
0%
#1935000
b110 ;
1%
#1940000
0%
#1945000
b111 ;
1%
#1950000
0%
#1955000
b1000 ;
1%
#1960000
0%
#1965000
b1001 ;
1%
#1970000
0%
#1975000
b1010 ;
1%
#1980000
0%
#1985000
b1011 ;
1%
#1990000
0%
#1995000
b1100 ;
1%
#2000000
0%
#2005000
b1101 ;
1%
#2010000
0%
#2015000
b1110 ;
1%
#2020000
0%
#2025000
b1111 ;
1%
#2030000
0%
#2035000
b10000 ;
1%
#2040000
0%
#2045000
b10001 ;
1%
#2050000
0%
#2055000
b10010 ;
1%
#2060000
0%
#2065000
b10011 ;
1%
#2070000
0%
#2075000
b10100 ;
1%
#2080000
0%
#2085000
b0 ;
1%
#2090000
0%
#2095000
b1 ;
1%
#2100000
0%
#2105000
b10 ;
1%
#2110000
0%
#2115000
b11 ;
1%
#2120000
0%
#2125000
b100 ;
1%
#2130000
0%
#2135000
b101 ;
1%
#2140000
0%
#2145000
b110 ;
1%
#2150000
0%
#2155000
b111 ;
1%
#2160000
0%
#2165000
b1000 ;
1%
